MANIFEST.in
README.md
setup.py
django_connection_pool/__init__.py
django_connection_pool.egg-info/PKG-INFO
django_connection_pool.egg-info/SOURCES.txt
django_connection_pool.egg-info/dependency_links.txt
django_connection_pool.egg-info/requires.txt
django_connection_pool.egg-info/top_level.txt
django_connection_pool/mysql/__init__.py
django_connection_pool/mysql/base.py
django_connection_pool/mysql/orm_patch.py
django_connection_pool/mysql/pool.py