Metadata-Version: 1.2
Name: django-connection-pool
Version: 1.2.0
Summary: django connection pool
Home-page: UNKNOWN
Author: Lee
Author-email: canyun@live.com
License: GNU General Public License v3.0
Platform: UNKNOWN
Requires-Python: >=3.7
